worst/__init__.py
worst-0.1.0.dist-info/METADATA
worst-0.1.0.dist-info/WHEEL
worst-0.1.0.dist-info/RECORD
